intelli3text/__init__.py
intelli3text/__main__.py
intelli3text/builder.py
intelli3text/config.py
intelli3text/errors.py
intelli3text/pipeline.py
intelli3text/utils.py
intelli3text/cleaners/__init__.py
intelli3text/cleaners/base.py
intelli3text/cleaners/chain.py
intelli3text/cleaners/clean_text.py
intelli3text/cleaners/pdf_linebreaks.py
intelli3text/cleaners/unicode_ftfy.py
intelli3text/export/__init__.py
intelli3text/export/base.py
intelli3text/export/jsonl.py
intelli3text/export/pdf_reportlab.py
intelli3text/extractors/__init__.py
intelli3text/extractors/base.py
intelli3text/extractors/file_docx.py
intelli3text/extractors/file_pdfminer.py
intelli3text/extractors/file_text.py
intelli3text/extractors/web_trafilatura.py
intelli3text/lid/__init__.py
intelli3text/lid/base.py
intelli3text/lid/cld3_lid.py
intelli3text/lid/fasttext_lid.py
intelli3text/nlp/__init__.py
intelli3text/nlp/base.py
intelli3text/nlp/registry.py
intelli3text/nlp/spacy_normalizer.py
intelli3text-0.2.3.dist-info/licenses/LICENSE
intelli3text-0.2.3.dist-info/METADATA
intelli3text-0.2.3.dist-info/WHEEL
intelli3text-0.2.3.dist-info/entry_points.txt
intelli3text-0.2.3.dist-info/top_level.txt
intelli3text-0.2.3.dist-info/RECORD
