Metadata-Version: 2.4
Name: intelli3text
Version: 0.2.3
Summary: Ingestion (web/PDF/DOCX/TXT), cleaning, paragraph-level LID (PT/EN/ES), and spaCy-based normalization; PDF export. Just pip install.
Author-email: Jefferson Rodrigo Speck <jeffersonspeck@msn.com>
License: MIT
Project-URL: Homepage, https://github.com/jeffersonspeck/intelli3text
Project-URL: Repository, https://github.com/jeffersonspeck/intelli3text
Project-URL: Issues, https://github.com/jeffersonspeck/intelli3text/issues
Project-URL: Documentation, https://jeffersonspeck.github.io/intelli3text/
Keywords: NLP,spaCy,language id,LID,cleaning,normalization,PDF,web extraction,text processing,Portuguese,Spanish,English
Classifier: Development Status :: 4 - Beta
Classifier: Intended Audience :: Developers
Classifier: Intended Audience :: Science/Research
Classifier: License :: OSI Approved :: MIT License
Classifier: Programming Language :: Python
Classifier: Programming Language :: Python :: 3
Classifier: Programming Language :: Python :: 3.9
Classifier: Programming Language :: Python :: 3.10
Classifier: Programming Language :: Python :: 3.11
Classifier: Programming Language :: Python :: 3.12
Classifier: Topic :: Scientific/Engineering :: Information Analysis
Classifier: Topic :: Text Processing :: Linguistic
Classifier: Operating System :: OS Independent
Requires-Python: >=3.9
License-File: LICENSE
Requires-Dist: numpy==1.26.4
Requires-Dist: thinc==8.2.4
Requires-Dist: spacy==3.7.4
Requires-Dist: trafilatura>=1.8
Requires-Dist: jusText>=3.0
Requires-Dist: lxml[html_clean]>=5.2
Requires-Dist: pdfminer.six>=20220524
Requires-Dist: python-docx>=1.1
Requires-Dist: ftfy>=6.2
Requires-Dist: clean-text>=0.6
Requires-Dist: requests>=2.32
Requires-Dist: reportlab>=4.1
Requires-Dist: Unidecode>=1.3.8
Requires-Dist: fasttext-wheel>=0.9.2
Provides-Extra: cld3
Requires-Dist: pycld3>=0.22; extra == "cld3"
Dynamic: license-file
